envprobe/__init__.py
envprobe/__main__.py
envprobe/compatibility.py
envprobe/environment.py
envprobe/library.py
envprobe/main.py
envprobe/setupped_main.py
envprobe/vartype_heuristics.py
envprobe/commands/__init__.py
envprobe/commands/add.py
envprobe/commands/consume.py
envprobe/commands/core.py
envprobe/commands/delete.py
envprobe/commands/descriptions.py
envprobe/commands/diff.py
envprobe/commands/get.py
envprobe/commands/hook.py
envprobe/commands/list.py
envprobe/commands/load.py
envprobe/commands/remove.py
envprobe/commands/save.py
envprobe/commands/set.py
envprobe/commands/set_variable.py
envprobe/commands/shortcuts.py
envprobe/commands/track.py
envprobe/commands/undefine.py
envprobe/community_descriptions/__init__.py
envprobe/community_descriptions/downloader.py
envprobe/community_descriptions/local_data.py
envprobe/community_descriptions/schema_doc.py
envprobe/settings/__init__.py
envprobe/settings/config_file.py
envprobe/settings/core.py
envprobe/settings/snapshot.py
envprobe/settings/variable_information.py
envprobe/settings/variable_tracking.py
envprobe/shell/__init__.py
envprobe/shell/bash.py
envprobe/shell/bash_like.py
envprobe/shell/core.py
envprobe/shell/zsh.py
envprobe/vartypes/__init__.py
envprobe/vartypes/array.py
envprobe/vartypes/colon_separated.py
envprobe/vartypes/envvar.py
envprobe/vartypes/numeric.py
envprobe/vartypes/path.py
envprobe/vartypes/semi_separated.py
envprobe/vartypes/string.py
envprobe-1.0.dist-info/LICENSE
envprobe-1.0.dist-info/METADATA
envprobe-1.0.dist-info/WHEEL
envprobe-1.0.dist-info/entry_points.txt
envprobe-1.0.dist-info/top_level.txt
envprobe-1.0.dist-info/RECORD
