Metadata-Version: 2.1
Name: envprobe
Version: 1.0
Summary: Overlaying pluggable environment setter: modules reimagined + toggleable direnv on the shell, rather than the directory level.
Home-page: http://github.com/whisperity/envprobe
Author: Whisperity
Author-email: whisperity-packages@protonmail.com
License: GPLv3+
Keywords: shell environment environment-variables bash zsh
Platform: UNKNOWN
Classifier: Development Status :: 5 - Production/Stable
Classifier: Environment :: Console
Classifier: Intended Audience :: End Users/Desktop
Classifier: Intended Audience :: Information Technology
Classifier: Intended Audience :: System Administrators
Classifier: License :: OSI Approved :: GNU General Public License v3 or later (GPLv3+)
Classifier: Operating System :: MacOS
Classifier: Operating System :: POSIX :: Linux
Classifier: Operating System :: Unix
Classifier: Programming Language :: Python :: 3 :: Only
Classifier: Topic :: Software Development
Classifier: Topic :: System :: Shells
Requires-Python: >=3.6
License-File: LICENSE
